Workbook

Sheet Proyeccion
A3: Casa Villa Carolina Gastos | B3: Total | C3: Tienda | D3: Recibo | E3: Deposito | F3: Restante | G3: Pago | H3: Quien Pago | I3: Jaiver Calderon | J3: Arnaldo Aponte | K3: Fecha | L3: Comentario
A4: Sellado de techo/estucado/pintura/jardin | B4: 4500 | C4: Jose | E4: 4500 | F4: =B4-E4 -> 0 | H4: Jose Javier Calderon / Arnaldo Aponte | I4: 2250 | J4: 2250 | K4: 46305 | L4: Se pago comleto a Jose
A5: Electricista | B5: 1100 | C5: Rigo Electric | E5: 1100 | F5: =B5-E5 -> 0 | G5: X | H5: Jose Javier Calderon / Arnaldo Aponte | I5: 550 | J5: 550 | K5: 46253
A6: Electricista | B6: 98 | C6: Rigo Electric | E6: 98 | F6: =B6-E6 -> 0 | G6: X | H6: Jose Javier Calderon / Arnaldo Aponte | I6: 49 | J6: 49 | K6: 8/27/20226 | L6: Se pago por cotizacion - Se le resto al trabajo
A7: Ebanistaria | B7: 150 | C7: jbmProjectsPr | E7: 150 | F7: =B7-E7 -> 0 | G7: X | H7: Jose Javier Calderon / Arnaldo Aponte | I7: 75 | J7: 75 | K7: 46254 | L7: Se pago por cotizacion - Cotizacion muy alta
A8: Miscelaneos - Materiales Jose Techo | B8: 492.79 | C8: Home Depot | D8: C7LUN-PDG6U | E8: 492.79 | F8: =B8-E8 -> 0 | G8: X | H8: Jose Javier Calderon / Arnaldo Aponte | I8: =E8/2 -> 246.395 | J8: 246.4 | K8: 46286 | L8: CROSSCO 8500, HARRIS TITANIUM FLAT, 2 PEGA
A9: Shipping Hammer Milwaukee | B9: 348.95 | C9: Home Depot | D9: DP3TP-THSC3 | E9: 348.95 | F9: =B9-E9 -> 0 | G9: X | H9: Jose Javier Calderon / Arnaldo Aponte | I9: =E9/2 -> 174.475 | J9: 174.48 | K9: 08/29/20226 | L9: Herramientas
A10: Wet Tile Saw | B10: 279.55 | C10: Home Depot | D10: FX5FD-P71PL | E10: 279.55 | F10: =B10-E10 -> 0 | G10: X | H10: Jose Javier Calderon / Arnaldo Aponte | I10: =E10/2 -> 139.775 | J10: 139.78 | K10: 08/05/26 | L10: Herramientas (Tile Saw)
A11: 1 Puerta - Back Patio | B11: 400 | C11: Luis Mercado | E11: 200 | F11: =B11-E11 -> 200 | G11: X | H11: Jose Javier Calderon / Arnaldo Aponte | I11: 200 | J11: 200 | K11: 46288 | L11: Pago
A12: Renta de Maquina Presion | B12: 116.5 | C12: JD EQUIMENT & SUPPLY INC | D12: 4KFHH9E8MQAEP | E12: 116.5 | F12: =B12-E12 -> 0 | G12: X | H12: Jose Javier Calderon | I12: =E12/2 -> 58.25 | J12: 58.25 | K12: 46274 | L12: Maquina de presion Alquilada para el techo
A13: Cocina | B13: 4240 | C13: Dario | D13: 1753 | E13: 2240 | F13: =B13-E13 -> 2000 | H13: Jose Javier Calderon / Arnaldo Aponte | I13: 1500 | J13: 740 | K13: 46304
A14: Baño | B14: 193.1 | C14: Home Depot | D14: VPDSH-E8W4N | E14: 193.1 | F14: =B14-E14 -> 0 | H14: Jose Javier Calderon | I14: 193.1 | L14: Ducha baño pasillo
A15: Piso - Instalacion de losas | B15: 4000 | C15: Jose | E15: 2000 | F15: =B15-E15 -> 2000 | I15: 2000 | L15: Pago por instalacion de Losas
A16: Piso - Losas | B16: 2892.31 | C16: Carolina Tile Outlet | E16: 2892.31 | F16: =B16-E16 -> 0 | G16: X | H16: Jose Javier Calderon | I16: 2892.31 | L16: 1.69 ft losa 24" x 24"
A17: Piso - Envio | B17: 250 | C17: Juan Acevedo -Carolina Tile Outlet | E17: 250 | F17: =B17-E17 -> 0 | G17: X | H17: Jose Javier Calderon | I17: 250 | L17: Envio de losas - ATH Movil
A18: Bloques - Pegas de losa - Herramientas | B18: 210.87 | C18: Home Depot | D18: U9UW5-TWY73 | E18: 210.87 | F18: =B18-E18 -> 0 | G18: X | H18: Arnaldo Aponte | J18: 210.87 | L18: Bloques - Pegas de losa - Herramientas
A19: Renta de maquina de rotos de deshagues y Disco d 5" para Canaletas | B19: 189.51 | C19: JD EQUIMENT & SUPPLY INC | D19: XZFRQAK19HR1R | E19: 189.51 | F19: =B19-E19 -> 0 | G19: X | H19: Jose Javier Calderon | I19: 169.97 | K19: 46288 | L19: Renta de maquina de rotos de deshagues y Disco d 5" para Canaletas
A20: Angualares | B20: 17.06 | C20: MARKET CHINA | D20: 345242 | E20: 17.06 | F20: =B20-E20 -> 0 | G20: X | H20: Jose Javier Calderon | I20: 17.06 | K20: 46294 | L20: Angualares
A21: Ferreteria - Colmado Agulares | B21: 51.41 | C21: Pepito Food Market | D21: C3202583 | E21: 51.41 | F21: =B21-E21 -> 0 | G21: X | H21: Jose Javier Calderon | I21: 51.41 | K21: 46293 | L21: Ferreteria - Colmado Agulares
A22: Compra de tornillos y base para receptaculos | B22: 8.99 | C22: National Lumber | E22: 8.99 | F22: =B22-E22 -> 0 | G22: X | H22: Jose Javier Calderon | I22: 8.99 | K22: 46295 | L22: Compra de tornillos y base para receptaculos
A23: Piso- LASH FLOOR LEVE CLIP | B23: 232.58 | C23: Home Depot | D23: 8X4GH-HF2TV | E23: 232.58 | F23: =B23-E23 -> 0 | G23: X | H23: Jose Javier Calderon | I23: 232.58 | K23: 46295 | L23: LASH FLOOR LEVE CLIP
A24: Door locks,Gosnes, Pintura de Bañera - Misc | B24: 257.33 | C24: Amazon | H24: Jose Javier Calderon | K24: 46302 | L24: Door locks,Gosnes, Pintura de Bañera - Misc
A25: Bañ ducha- Sellador de techo - Miscelaneos | B25: 411.64 | C25: HomeDepot | H25: Arnaldo Aponte | K25: 46302 | L25: Bañ ducha- Sellador de techo - Miscelaneos
A27: 11 Ventanas - Cocina - Sala- Frente | B27: 3495 | C27: Javier - Ventanas | E27: 0 | F27: =B27-E27 -> 3495
A28: 2 fijos - frente | B28: 458 | C28: Air Master | E28: 0 | F28: =B28-E28 -> 458
A29: 2 Puertas - Cocina | B29: 0 | C29: Luis Mercado | E29: 0 | F29: =B29-E29 -> 0
B30: =SUM(B4:B28) -> 24393.59 | C30: =25000-B30 -> 606.41 | D30: (Restante para un budget de 25K) | E30: =SUM(E4:E28) -> 15571.62 | F30: =SUM(F4:F28) -> 8153 | I30: =SUM(I4:I28) -> 11058.315 | J30: =SUM(J4:J28) -> 4693.78
C36: 310 | D36: 19 | E36: =C36*D36 -> 5890

Sheet Gastos (App)
A1: ID | B1: Fecha | C1: Categoría | D1: Descripción | E1: Suplidor | F1: # Recibo | G1: Total | H1: Pagó Jose | I1: Pagó Arnaldo | J1: Pendiente | K1: Comentario | L1: Para revisar | M1: Documento
A2: 1 | B2: 46223 | C2: Adquisición | D2: Precio de compra – cheque a vendedor (Enrique Rodríguez) | E2: Banco Popular | F2: 103114600016304 | G2: 71182 | H2: 71182 | I2: 0 | J2: =G2-H2-I2 | K2: Cheque oficial | M2: Cheques Pago Total07272026.pdf
A3: 2 | B3: 46223 | C3: Adquisición | D3: Precio de compra – cheque a vendedora (Lissa Dávila) | E3: Banco Popular | F3: 103114600016302 | G3: 71182 | H3: 0 | I3: 71182 | J3: =G3-H3-I3 | K3: Cheque oficial | M3: Cheques Pago Total07272026.pdf
A4: 3 | B4: 46223 | C4: Adquisición | D4: Factura legal parte vendedora (descontada del precio) | E4: Lcda. Lesbia Hernández | F4: 103114600016303 | G4: 2636 | H4: 0 | I4: 2636 | J4: =G4-H4-I4 | K4: Parte del precio de $150,000 | M4: Cheques Pago Total07272026.pdf
A5: 4 | B5: 46180 | C5: Adquisición | D5: Depósito de buena fe | E5: — | G5: 5000 | H5: 2500 | I5: 2500 | J5: =G5-H5-I5 | K5: Parte del precio de $150,000 | L5: ¿Quién pagó el depósito? Se asumió 50/50 — corregir | M5: Contrato Compra y Venta Casa Villa Carolina06072026 (1).pdf
A6: 5 | B6: 46223 | C6: Cierre / Legal | D6: Factura legal parte compradora (escritura, aranceles, CRIM) | E6: Lcda. Lesbia Hernández | G6: 1199.5 | H6: 599.75 | I6: 599.75 | J6: =G6-H6-I6 | L6: ¿Quién pagó? Se asumió 50/50 — corregir | M6: Factura y desglose de pago por gastos legales07272026.pdf
A7: 6 | B7: 46223 | C7: Cierre / Legal | D7: Cargos de cheques oficiales (3 × $10) | E7: Banco Popular | G7: 30 | H7: 10 | I7: 20 | J7: =G7-H7-I7 | M7: Cheques Pago Total07272026.pdf
A8: 7 | C8: Techo / Exterior | D8: Sellado de techo / estucado / pintura / jardín | E8: Jose | G8: 4500 | H8: 1750 | I8: 2250 | J8: =G8-H8-I8 | K8: Restan $500
A9: 8 | B9: 46253 | C9: Electricidad | D9: Electricista | E9: Rigo Electric | G9: 1100 | H9: 550 | I9: 550 | J9: =G9-H9-I9
A10: 9 | B10: 46261 | C10: Electricidad | D10: Electricista (cotización, se restó del trabajo) | E10: Rigo Electric | G10: 98 | H10: 49 | I10: 49 | J10: =G10-H10-I10 | K10: Se pagó por cotización
A11: 10 | B11: 46254 | C11: Cocina | D11: Ebanistería – cotización | E11: jbmProjectsPr | G11: 150 | H11: 75 | I11: 75 | J11: =G11-H11-I11 | K11: Cotización muy alta
A12: 11 | B12: 46286 | C12: Techo / Exterior | D12: Materiales techo (Crossco 8500, Harris, pega) | E12: Home Depot | F12: C7LUN-PDG6U | G12: 492.79 | H12: 246.39 | I12: 246.4 | J12: =G12-H12-I12 | M12: Home Depot $492.79 Sep 21 2026 eReceipt.pdf
A13: 12 | B13: 46263 | C13: Herramientas / Equipo | D13: Hammer Milwaukee (shipping) | E13: Home Depot | F13: DP3TP-THSC3 | G13: 348.95 | H13: 174.47 | I13: 174.48 | J13: =G13-H13-I13 | K13: Herramientas | M13: Home Depot $348.95 Aug 29 2026 eReceipt.pdf
A14: 13 | B14: 46239 | C14: Herramientas / Equipo | D14: Wet Tile Saw | E14: Home Depot | F14: FX5FD-P71PL | G14: 279.55 | H14: 139.77 | I14: 139.78 | J14: =G14-H14-I14 | M14: Home Depot 279.55 Aug 5 2026 - Tile Cutter- eReceipt.pdf
A15: 14 | B15: 46288 | C15: Puertas / Ventanas | D15: 1 puerta – back patio | E15: Luis Mercado | G15: 400 | H15: 200 | I15: 200 | J15: =G15-H15-I15 | L15: Excel: depósito $200 pero Jose $200 + Arnaldo $200 = $400. Verificar
A16: 15 | B16: 46274 | C16: Techo / Exterior | D16: Renta máquina de presión (techo) | E16: JD Equipment & Supply | F16: 4KFHH9E8MQAEP | G16: 116.5 | H16: 58.25 | I16: 58.25 | J16: =G16-H16-I16
A17: 16 | B17: 46304 | C17: Cocina | D17: Cocina – gabinetes/instalación | E17: Dario | F17: 1753 | G17: 4240 | H17: 1500 | I17: 740 | J17: =G17-H17-I17 | K17: Restan $2,000 | M17: planso de cocina lower.png
A18: 17 | C18: Baño | D18: Ducha baño pasillo y switch de luces | E18: Home Depot | G18: 492.79 | H18: 492.79 | I18: 0 | J18: =G18-H18-I18 | L18: Mismo monto que la compra de techo del 21-sep ($492.79). ¿Duplicado? El recibo de ducha es $193.10 | M18: Home Depot $193.10 Aug 1 2026 - Shower - eReceipt.pdf
A19: 18 | C19: Piso | D19: Instalación de losas | E19: Jose | G19: 4000 | H19: 2000 | I19: 0 | J19: =G19-H19-I19 | K19: Restan $2,000
A20: 19 | C20: Piso | D20: Losas 24"×24" | E20: Carolina Tile Outlet | G20: 2892.31 | H20: 2892.31 | I20: 0 | J20: =G20-H20-I20 | K20: 1.69 ft² losa 24×24 | M20: losas 24 x 24 1.30 home depot.png
A21: 20 | C21: Piso | D21: Envío de losas (ATH Móvil) | E21: Juan Acevedo – Carolina Tile Outlet | G21: 250 | H21: 250 | I21: 0 | J21: =G21-H21-I21
A22: 21 | B22: 46295 | C22: Piso | D22: Bloques, pegas de losa, herramientas | E22: Home Depot | F22: U9UW5-TWY73 | G22: 210.87 | H22: 0 | I22: 210.87 | J22: =G22-H22-I22 | M22: Home Depot $210 Spet 30 2026 eReceipt.pdf
A23: 22 | B23: 46288 | C23: Herramientas / Equipo | D23: Renta máquina destapar desagües + disco 5" canaletas | E23: JD Equipment & Supply | F23: XZFRQAK19HR1R | G23: 189.51 | H23: 189.51 | I23: 0 | J23: =G23-H23-I23 | L23: Excel muestra $169.97 pagado vs. total $189.51. Verificar
A24: 23 | B24: 46294 | C24: Misceláneos | D24: Angulares | E24: Market China | F24: 345242 | G24: 17.06 | H24: 17.06 | I24: 0 | J24: =G24-H24-I24
A25: 24 | B25: 46293 | C25: Misceláneos | D25: Ferretería – angulares | E25: Pepito Food Market | F25: C3202583 | G25: 51.41 | H25: 51.41 | I25: 0 | J25: =G25-H25-I25
A26: 25 | B26: 46295 | C26: Electricidad | D26: Tornillos y bases para receptáculos | E26: National Lumber | G26: 8.99 | H26: 8.99 | I26: 0 | J26: =G26-H26-I26
A27: 26 | B27: 46295 | C27: Piso | D27: Lash floor level clip | E27: Home Depot | F27: 8X4GH-HF2TV | G27: 232.58 | H27: 232.58 | I27: 0 | J27: =G27-H27-I27
A28: 27 | B28: 46302 | C28: Misceláneos | D28: Door locks, goznes, pintura de bañera | E28: Amazon | G28: 257.33 | H28: 257.33 | I28: 0 | J28: =G28-H28-I28 | L28: Pago no registrado en Excel; se asumió pagado por Jose
A29: 28 | B29: 46302 | C29: Baño | D29: Ducha, sellador de techo, misceláneos | E29: Home Depot | G29: 411.64 | H29: 0 | I29: 411.64 | J29: =G29-H29-I29 | L29: Pago no registrado en Excel; se asumió pagado por Arnaldo | M29: Home Depot 411.64 Octubre 7 2026 -Shower-Sellado de Techo .pdf
A30: 29 | C30: Puertas / Ventanas | D30: 11 ventanas – cocina, sala, frente | E30: Javier – Ventanas | G30: 3495 | H30: 0 | I30: 0 | J30: =G30-H30-I30 | K30: Pendiente
A31: 30 | C31: Puertas / Ventanas | D31: 2 fijos – frente | E31: Air Master | G31: 458 | H31: 0 | I31: 0 | J31: =G31-H31-I31 | K31: Pendiente
A32: 31 | C32: Puertas / Ventanas | D32: 2 puertas – cocina | E32: Luis Mercado | G32: 0 | H32: 0 | I32: 0 | J32: =G32-H32-I32 | K32: Falta cotización | L32: Sin precio todavía
A33: TOTAL | G33: =SUM(G2:G32) | H33: =SUM(H2:H32) | I33: =SUM(I2:I32) | J33: =SUM(J2:J32)

Sheet Resumen (App)
A1: Casa Villa Carolina — Resumen
A2: Edita los valores en amarillo; la app los toma al sincronizar.
A3: Supuestos | B3: Valor | C3: (clave)
A4: Precio de venta meta ($) | B4: 260000 | C4: salePrice
A5: Comisión corredor (%) | B5: 5 | C5: commissionPct
A6: Gastos de cierre del vendedor ($) | B6: 3000 | C6: sellerClosing
A7: Presupuesto remodelación ($) | B7: 25000 | C7: renoBudget
A8: ROI meta (%) | B8: 20 | C8: targetRoi
A9: Repartir ganancia (capital o 50/50) | B9: capital | C9: profitSplit
A11: Resultados (se calculan solos)
A12: Compra (adquisición) | B12: =SUMIFS('Gastos (App)'!$G$2:$G$32,'Gastos (App)'!$C$2:$C$32,"Adquisición")
A13: Cierre / legal | B13: =SUMIFS('Gastos (App)'!$G$2:$G$32,'Gastos (App)'!$C$2:$C$32,"Cierre / Legal")
A14: Remodelación | B14: =SUM('Gastos (App)'!$G$2:$G$32)-B12-B13
A15: Inversión total | B15: =SUM('Gastos (App)'!$G$2:$G$32)
A16: Costos de venta (comisión + cierre) | B16: =B4*B5/100+B6
A17: GANANCIA NETA PROYECTADA | B17: =B4-B16-B15
A18: % Ganancia (ROI) | B18: =IFERROR(B17/B15,0)
A19: Margen sobre venta | B19: =IFERROR(B17/B4,0)
A20: Punto de equilibrio | B20: =(B15+B6)/(1-B5/100)
A21: Presupuesto remodelación disponible | B21: =B7-B14
A22: Pagado hasta hoy | B22: =SUM('Gastos (App)'!$H$2:$I$32)
A23: Pendiente por pagar | B23: =SUM('Gastos (App)'!$J$2:$J$32)
A24: Aportado por Jose | B24: =SUM('Gastos (App)'!$H$2:$H$32)
A25: Aportado por Arnaldo | B25: =SUM('Gastos (App)'!$I$2:$I$32)
